callbackaun/__init__.py
callbackaun/alrcallback/__init__.py
callbackaun/alrcallback/alrcallback.py
callbackaun-0.0.2.dist-info/LICENSE
callbackaun-0.0.2.dist-info/METADATA
callbackaun-0.0.2.dist-info/WHEEL
callbackaun-0.0.2.dist-info/top_level.txt
callbackaun-0.0.2.dist-info/RECORD
