Metadata-Version: 2.1
Name: callbackaun
Version: 0.0.2
Summary: Callbackaun: Custom Callbacks that will control training
Home-page: https://github.com/shivamkc01/CallbackAUN_library
Author: Shivam Chhetry
Author-email: Shivam.11712711@gmail.com
License: MIT License
Platform: MacOS
Platform: MacOS X
Platform: Windows
Platform: linux
Platform: unix
Requires-Python: >3.5.2
License-File: LICENSE
Requires-Dist: scikit-learn (>=0.24.3)
